u0_stitcher/__init__.py
u0_stitcher/fisheye2Equirectangular.py
u0_stitcher/stitchEasy3.py
u0_stitcher/stitcher.py
your_library_name-0.1.0.dist-info/METADATA
your_library_name-0.1.0.dist-info/WHEEL
your_library_name-0.1.0.dist-info/top_level.txt
your_library_name-0.1.0.dist-info/RECORD
